PyThreadFlow/threadFlowManager/__init__.py
PyThreadFlow/threadFlowManager/advthreads.py
pythreadflow-0.0.0.dev3.dist-info/METADATA
pythreadflow-0.0.0.dev3.dist-info/WHEEL
pythreadflow-0.0.0.dev3.dist-info/licenses/LICENCE
pythreadflow-0.0.0.dev3.dist-info/RECORD
