Metadata-Version: 2.1
Name: PyThreadFlow
Version: 0.0.0.dev3
Summary: a python threadding extension meant to boost threading capabilities
Project-URL: Homepage, https://nilonic.github.io/PyThreadFlow/
Project-URL: Bug Tracker, https://github.com/nilonic/PyThreadFlow/issues
Author-email: Nilonic <nilonic.suggestions@gmail.com>
License-File: LICENCE
Classifier: License :: OSI Approved :: MIT License
Classifier: Operating System :: OS Independent
Classifier: Programming Language :: Python :: 3
Requires-Python: >=3.7
